genesia_cli/cli.py
genesia_cli-0.1.0.dist-info/METADATA
genesia_cli-0.1.0.dist-info/WHEEL
genesia_cli-0.1.0.dist-info/entry_points.txt
genesia_cli-0.1.0.dist-info/RECORD
