Metadata-Version: 2.1
Name: genesia-cli
Version: 0.1.0
Summary: genesia cli
License: MIT
Author: lucasmrdt
Author-email: lucas.marandat@gmail.com
Requires-Python: >=3.11,<4.0
Classifier: License :: OSI Approved :: MIT License
Classifier: Programming Language :: Python :: 3
Classifier: Programming Language :: Python :: 3.11
Requires-Dist: click (>=8.1.7,<9.0.0)
Requires-Dist: genesia-templates (>=0.1.5,<0.2.0)
Requires-Dist: python-socketio[client] (>=5.8.0,<6.0.0)
Requires-Dist: yaspin (>=3.0.0,<4.0.0)
